ding/__init__.py
ding/lookup.py
ding/otp.py
ding/sdk.py
ding/sdkconfiguration.py
ding/models/__init__.py
ding/models/errors/__init__.py
ding/models/errors/errorresponse.py
ding/models/errors/sdkerror.py
ding/models/operations/__init__.py
ding/models/operations/post_authentication.py
ding/models/operations/post_check.py
ding/models/operations/post_lookup.py
ding/models/operations/post_retry.py
ding/models/shared/__init__.py
ding/models/shared/createauthenticationrequest.py
ding/models/shared/createauthenticationresponse.py
ding/models/shared/createcheckrequest.py
ding/models/shared/createcheckresponse.py
ding/models/shared/lookuprequest.py
ding/models/shared/lookupresponse.py
ding/models/shared/retryauthenticationrequest.py
ding/models/shared/retryauthenticationresponse.py
ding/models/shared/security.py
ding/utils/__init__.py
ding/utils/retries.py
ding/utils/utils.py
ding_api_sdk-0.3.0.dist-info/LICENSE.md
ding_api_sdk-0.3.0.dist-info/METADATA
ding_api_sdk-0.3.0.dist-info/WHEEL
ding_api_sdk-0.3.0.dist-info/top_level.txt
ding_api_sdk-0.3.0.dist-info/RECORD
